utsavcalc/__init__.py
utsavcalc-0.2.dist-info/Licence.txt
utsavcalc-0.2.dist-info/METADATA
utsavcalc-0.2.dist-info/WHEEL
utsavcalc-0.2.dist-info/top_level.txt
utsavcalc-0.2.dist-info/RECORD
