Metadata-Version: 2.1
Name: utsavcalc
Version: 0.2
Summary: SUM/SUB/NUM/DIV
Home-page: UNKNOWN
Author: Utsav Chabhadiya
License: UNKNOWN
Platform: UNKNOWN
License-File: Licence.txt
